<images>
	<photo image="images/big/101.jpg">
	<![CDATA[<head>MOD:PC01  $200</head><body>Pastel de chocolate con fresas</body>]]></photo>
	
	<photo image="images/big/102.jpg">
	<![CDATA[<head>MOD:PC02  $250</head><br><body>Pastel sabor brownie con queso</body>]]></photo>
	
	<photo image="images/big/103.jpg">
	<![CDATA[<head>MOD:PC03  $200</head><br><body>Pastel sabor coco</body>]]></photo>
	
	<photo image="images/big/104.jpg">
	<![CDATA[<head>MOD:PC04  $220</head><body>Pastel de fresa</body>]]></photo>
	
	<photo image="images/big/105.jpg">
	<![CDATA[<head>MOD:PC05  $230</head><body>Pastel sabor chocolate con frambuesas encima</body>]]></photo>
	
	<photo image="images/big/106.jpg">
	<![CDATA[<head>MOD:PC06  $210</head><body>Pastel de durazno y galaletas con un toque de canela</body>]]></photo>
	
	<photo image="images/big/107.jpg">
	<![CDATA[<head>MOD:PC07  $250</head><body>Pastel sabor milkyway</body>]]></photo>
	
	<photo image="images/big/108.jpg">
	<![CDATA[<head>MOD:PC08  $210</head><body>Pastel sabor piña colada</body>]]></photo>
	
	<photo image="images/big/109.jpg">
	<![CDATA[<head>MOD:PC09  $240</head><body>Pastel sabor pinguino</body>]]></photo>
	
	<photo image="images/big/110.jpg">
	<![CDATA[<head>MOD:PC10  $250</head><body>Rosca sabor moka</body>]]></photo>
	
</images>
